.editorconfig
.gitignore
.gitlab-ci.yml
LICENSE
README.rst
publish.settings.sh
publish.sh
pyproject.toml
.idea/modules.xml
.idea/peek-office-app.iml
.idea/inspectionProfiles/Project_Default.xml
.idea/inspectionProfiles/profiles_settings.xml
peek_office_app/.browserslistrc
peek_office_app/.gitignore
peek_office_app/PlatformDependencyTest.py
peek_office_app/README.md
peek_office_app/__init__.py
peek_office_app/angular.json
peek_office_app/karma.conf.js
peek_office_app/ngsw-config.json
peek_office_app/package-lock.json
peek_office_app/package.json
peek_office_app/protractor.conf.js
peek_office_app/proxy.conf.json
peek_office_app/tsconfig.app.json
peek_office_app/tsconfig.json
peek_office_app/tsconfig.spec.json
peek_office_app/tsconfig.worker.json
peek_office_app.egg-info/PKG-INFO
peek_office_app.egg-info/SOURCES.txt
peek_office_app.egg-info/dependency_links.txt
peek_office_app.egg-info/requires.txt
peek_office_app.egg-info/top_level.txt
peek_office_app/e2e/app.e2e-spec.ts
peek_office_app/e2e/app.po.ts
peek_office_app/e2e/tsconfig.e2e.json
peek_office_app/src/_components.scss
peek_office_app/src/_variables.scss
peek_office_app/src/favicon.ico
peek_office_app/src/index.html
peek_office_app/src/main.ts
peek_office_app/src/manifest.webmanifest
peek_office_app/src/polyfills.ts
peek_office_app/src/styles.scss
peek_office_app/src/test.ts
peek_office_app/src/typings.d.ts
peek_office_app/src/app/app.module.ts
peek_office_app/src/app/app.routes.ts
peek_office_app/src/app/app.services.ts
peek_office_app/src/app/plugin-root.component.ts
peek_office_app/src/app/core/index.ts
peek_office_app/src/app/core/components/components.module.ts
peek_office_app/src/app/core/components/index.ts
peek_office_app/src/app/core/components/app/app.component.html
peek_office_app/src/app/core/components/app/app.component.scss
peek_office_app/src/app/core/components/app/app.component.ts
peek_office_app/src/app/core/components/app/index.ts
peek_office_app/src/app/core/components/sidebar/index.ts
peek_office_app/src/app/core/components/sidebar/sidebar.component.html
peek_office_app/src/app/core/components/sidebar/sidebar.component.scss
