Metadata-Version: 2.4
Name: peek-office-app
Version: 5.0.4
Summary: Peek Office UI App - the Angular Web build for Peek Office
Author-email: Synerty <contact@synerty.com>
Project-URL: Homepage, https://github.com/Synerty/peek-office-app
Keywords: Peek,Python,Platform,synerty
License-File: LICENSE
Requires-Dist: peek-plugin-base==5.0.4
Dynamic: license-file
